wind_farm_loads/__init__.py
wind_farm_loads/_floris_solver.py
wind_farm_loads/floris.py
wind_farm_loads/py_wake.py
wind_farm_loads/tool_agnostic.py
wind_farm_loads-0.20.5.dist-info/METADATA
wind_farm_loads-0.20.5.dist-info/WHEEL
wind_farm_loads-0.20.5.dist-info/licenses/LICENSES_bundled.txt
wind_farm_loads-0.20.5.dist-info/RECORD
